ej_cli/__init__.py
ej_cli/__main__.py
ej_cli/attendance/__init__.py
ej_cli/attendance/attendance.py
ej_cli/auth/__init__.py
ej_cli/auth/exceptions.py
ej_cli/auth/user.py
ej_cli/classroom/__init__.py
ej_cli/classroom/classroom.py
ej_cli/kanban/__init__.py
ej_cli/kanban/kanban.py
ej_cli/loader/__init__.py
ej_cli/loader/loader.py
ej_cli/map/__init__.py
ej_cli/map/map.py
ej_cli/saved/__init__.py
ej_cli/sis/__init__.py
ej_cli/sis/caltemplate.py
ej_cli/sis/gcalendar.py
ej_cli/sis/regex.py
ej_cli/sis/schedule.py
ej_cli/sis/sis.py
ej_cli/wifi/__init__.py
ej_cli/wifi/linuxwifi.py
ej_cli/wifi/macwifi.py
ej_cli/wifi/myos.py
ej_cli/wifi/wifi.py
ej_cli/wifi/winwifi.py
ejustian_cli-1.0.0.dist-info/LICENSE
ejustian_cli-1.0.0.dist-info/METADATA
ejustian_cli-1.0.0.dist-info/WHEEL
ejustian_cli-1.0.0.dist-info/entry_points.txt
ejustian_cli-1.0.0.dist-info/top_level.txt
ejustian_cli-1.0.0.dist-info/RECORD
