Metadata-Version: 2.1
Name: ejustian-cli
Version: 1.0.0
Summary: A command line interface app that allows EJUST students to manage all their stuff.
Author: Abdelrahman Wael Abdelkhalek
Author-email: abdelrahman0w@gmail.com
License: MIT
Requires-Python: >=3.8.*
License-File: LICENSE
Requires-Dist: requests
Requires-Dist: beautifulsoup4
Requires-Dist: lxml
Requires-Dist: inquirer
Requires-Dist: tabulate
Requires-Dist: python-kanban
Requires-Dist: google-api-python-client
Requires-Dist: google-auth-httplib2
Requires-Dist: google-auth-oauthlib
Requires-Dist: pydantic
